{
  "sections": {
    "global_page_header_banner_hKKRYq": {
      "type": "global-page-header-banner",
      "blocks": {
        "page_banner_LrgGT6": {
          "type": "_page_banner",
          "settings": {
            "first_image": "shopify:\/\/shop_images\/fluid-banner-015.jpg",
            "first_image_mobile": "shopify:\/\/shop_images\/mlouye-business-bag-earth-8_0703a3cb-d2d0-4d56-8218-c0eac1cfd14a.jpg",
            "enable_overlay": false,
            "overlay_bg_color": "#000000",
            "overlay_opacity": 0.3,
            "blend_mode": "none",
            "display": "d-flex",
            "direction": "flex-md-column",
            "direction_mobile": "flex-column",
            "wrap": "flex-nowrap",
            "align_items": "align-items-md-start",
            "align_items_mb": "align-items-start",
            "justify_content": "justify-content-md-center",
            "justify_content_mb": "justify-content-center"
          },
          "blocks": {
            "breadcrumbs_fwn9rB": {
              "type": "breadcrumbs",
              "settings": {
                "font_size": 13,
                "font_size_mb": 12,
                "breadcrumbs_divider": "slash",
                "breadcrumbs_position": "defalut-position",
                "font_weight": 400,
                "color": "#202124",
                "color_active": "#202124",
                "font_weight_active": 400,
                "mb-desktop": "mb-md-0",
                "mb-mobile": "mb-0"
              },
              "blocks": {}
            },
            "group_YWGN9V": {
              "type": "group",
              "settings": {
                "width": "col-lg-12",
                "width_md": "col-md-12",
                "width_sm": "col-12",
                "display": "d-flex",
                "direction": "flex-md-column",
                "direction_mobile": "flex-column",
                "wrap": "flex-nowrap",
                "align_items": "align-items-md-center",
                "align_items_mb": "align-items-center",
                "justify_content": "justify-content-md-start",
                "justify_content_mb": "justify-content-start",
                "padding_top_desktop": "pt-md-0",
                "padding_bottom_desktop": "pb-md-0",
                "padding_left_desktop": "ps-md-0",
                "padding_right_desktop": "pe-md-0",
                "padding_top_mobile": "pt-0",
                "padding_bottom_mobile": "pb-0",
                "padding_left_mobile": "ps-0",
                "padding_right_mobile": "pe-0",
                "gap_column": "column-gap-md-0",
                "gap_row": "row-gap-md-0",
                "gap_column_mobile": "column-gap-0",
                "gap_row_mobile": "row-gap-0",
                "bg_color": "transparent",
                "border": "border-0",
                "border_color": "#d5d5d5",
                "border_radius": 0
              },
              "blocks": {
                "heading_KBMRTe": {
                  "type": "heading",
                  "settings": {
                    "text": "<h1>{{ closest.page.title }}<\/h1>",
                    "text_size": "",
                    "font_family": "font-family-heading",
                    "alignment": "text-md-start",
                    "alignment_mobile": "text-start",
                    "color": "",
                    "margin_top_desktop": "mt-md-0",
                    "margin_bottom_desktop": "mb-md-0",
                    "margin_top_mobile": "mt-0",
                    "margin_bottom_mobile": "mb-0"
                  },
                  "blocks": {}
                }
              },
              "block_order": [
                "heading_KBMRTe"
              ]
            }
          },
          "block_order": [
            "breadcrumbs_fwn9rB",
            "group_YWGN9V"
          ]
        }
      },
      "block_order": [
        "page_banner_LrgGT6"
      ],
      "name": "Page Header Banner",
      "settings": {
        "fluid_layout": true,
        "height": "small",
        "caption_style": false,
        "section_bg_color": ""
      }
    },
    "main": {
      "type": "template-page",
      "disabled": true,
      "settings": {
        "fluid_layout": false,
        "section_top_spacing": "spacing-top-sm",
        "section_bottom_spacing": "spacing-bottom-sm"
      }
    }
  },
  "order": [
    "global_page_header_banner_hKKRYq",
    "main"
  ]
}
